guizero/App.py
guizero/Box.py
guizero/ButtonGroup.py
guizero/CheckBox.py
guizero/Combo.py
guizero/Drawing.py
guizero/ListBox.py
guizero/MenuBar.py
guizero/Picture.py
guizero/PushButton.py
guizero/RadioButton.py
guizero/Slider.py
guizero/Text.py
guizero/TextBox.py
guizero/TitleBox.py
guizero/Waffle.py
guizero/Window.py
guizero/__init__.py
guizero/base.py
guizero/dialog.py
guizero/event.py
guizero/tkmixins.py
guizero/utilities.py
guizero-1.5.1.dist-info/METADATA
guizero-1.5.1.dist-info/WHEEL
guizero-1.5.1.dist-info/RECORD
