Metadata-Version: 2.4
Name: guizero
Version: 1.5.1
Summary: Python module to allow learners to easily create GUIs
Project-URL: Repository, https://github.com/lawsie/guizero
Project-URL: Documentation, https://lawsie.github.io/guizero/
Author: Martin O'Hanlon
Author-email: Laura Sach <laura.sach@raspberrypi.org>
License: BSD-3-Clause
Keywords: GUI,guizero,interface
Classifier: Development Status :: 5 - Production/Stable
Classifier: Intended Audience :: Developers
Classifier: Intended Audience :: Education
Classifier: License :: OSI Approved :: BSD License
Classifier: Programming Language :: Python :: 3
Classifier: Programming Language :: Python :: 3.5
Classifier: Programming Language :: Python :: 3.6
Classifier: Programming Language :: Python :: 3.7
Classifier: Programming Language :: Python :: 3.8
Classifier: Programming Language :: Python :: 3.9
Classifier: Programming Language :: Python :: 3.10
Classifier: Programming Language :: Python :: 3.11
Classifier: Programming Language :: Python :: 3.12
Classifier: Topic :: Education
Classifier: Topic :: Software Development :: User Interfaces
Requires-Python: >=3
Provides-Extra: images
Requires-Dist: pillow>=4.3.0; extra == 'images'
